{
	"11001": {
		"menuId": "/contents/MDC/MDI/mdiLoader/index.cmd?menuId=MDC0201010101",
		"title": "전체지수 시세"
	},
	"11002": {
		"menuId": "/contents/MDC/MDI/mdiLoader/index.cmd?menuId=MDC0201010102",
		"title": "전체지수 등락률"
	},
	"11003": {
		"menuId": "/contents/MDC/MDI/mdiLoader/index.cmd?menuId=MDC0201010103",
		"title": "개별지수 시세 추이"
	},
	"11004": {
		"menuId": "/contents/MDC/MDI/mdiLoader/index.cmd?menuId=MDC0201010104",
		"title": "전체지수 기본정보"
	},
	"11005": {
		"menuId": "/contents/MDC/MDI/mdiLoader/index.cmd?menuId=MDC0201010105",
		"title": "개별지수 종합정보"
	},
	"11006": {
		"menuId": "/contents/MDC/MDI/mdiLoader/index.cmd?menuId=MDC0201010106",
		"title": "지수구성종목"
	},
	"11007": {
		"menuId": "/contents/MDC/MDI/mdiLoader/index.cmd?menuId=MDC0201010107",
		"title": "PER/PBR/배당수익률"
	},
	"11008": {
		"menuId": "/contents/MDC/MDI/mdiLoader/index.cmd?menuId=MDC0201010201",
		"title": "전체지수 시세"
	},
	"11009": {
		"menuId": "/contents/MDC/MDI/mdiLoader/index.cmd?menuId=MDC0201010202",
		"title": "개별지수 시세 추이"
	},
	"11010": {
		"menuId": "/contents/MDC/MDI/mdiLoader/index.cmd?menuId=MDC0201010301",
		"title": "전체지수 시세"
	},
	"11011": {
		"menuId": "/contents/MDC/MDI/mdiLoader/index.cmd?menuId=MDC0201010302",
		"title": "전체지수 등락률"
	},
	"11012": {
		"menuId": "/contents/MDC/MDI/mdiLoader/index.cmd?menuId=MDC0201010303",
		"title": "개별지수 시세 추이"
	},
	"11013": {
		"menuId": "/contents/MDC/MDI/mdiLoader/index.cmd?menuId=MDC0201010304",
		"title": "전체지수 기본정보"
	},
	"11014": {
		"menuId": "/contents/MDC/MDI/mdiLoader/index.cmd?menuId=MDC0201010305",
		"title": "개별지수 종합정보"
	},
	"12001": {
		"menuId": "/contents/MDC/MDI/mdiLoader/index.cmd?menuId=MDC0201020101",
		"title": "전종목 시세"
	},
	"12002": {
		"menuId": "/contents/MDC/MDI/mdiLoader/index.cmd?menuId=MDC0201020102",
		"title": "전종목 등락률"
	},
	"12003": {
		"menuId": "/contents/MDC/MDI/mdiLoader/index.cmd?menuId=MDC0201020103",
		"title": "개별종목 시세 추이"
	},
	"12004": {
		"menuId": "/contents/MDC/MDI/mdiLoader/index.cmd?menuId=MDC0201020104",
		"title": "개별종목 시세 추이(월)"
	},
	"12005": {
		"menuId": "/contents/MDC/MDI/mdiLoader/index.cmd?menuId=MDC0201020201",
		"title": "전종목 기본정보"
	},
	"12006": {
		"menuId": "/contents/MDC/MDI/mdiLoader/index.cmd?menuId=MDC0201020202",
		"title": "전종목 지정내역"
	},
	"12007": {
		"menuId": "/contents/MDC/MDI/mdiLoader/index.cmd?menuId=MDC0201020203",
		"title": "개별종목 종합정보"
	},
	"12008": {
		"menuId": "/contents/MDC/MDI/mdiLoader/index.cmd?menuId=MDC0201020301",
		"title": "투자자별 거래실적"
	},
	"12009": {
		"menuId": "/contents/MDC/MDI/mdiLoader/index.cmd?menuId=MDC0201020302",
		"title": "투자자별 거래실적(개별종목)"
	},
	"12010": {
		"menuId": "/contents/MDC/MDI/mdiLoader/index.cmd?menuId=MDC0201020303",
		"title": "투자자별 순매수상위종목"
	},
	"12011": {
		"menuId": "/contents/MDC/MDI/mdiLoader/index.cmd?menuId=MDC0201020304",
		"title": "대량매매(전일)"
	},
	"12012": {
		"menuId": "/contents/MDC/MDI/mdiLoader/index.cmd?menuId=MDC0201020305",
		"title": "프로그램매매"
	},
	"12013": {
		"menuId": "/contents/MDC/MDI/mdiLoader/index.cmd?menuId=MDC0201020401",
		"title": "REITs 시세"
	},
	"12014": {
		"menuId": "/contents/MDC/MDI/mdiLoader/index.cmd?menuId=MDC0201020402",
		"title": "뮤추얼펀드 시세"
	},
	"12015": {
		"menuId": "/contents/MDC/MDI/mdiLoader/index.cmd?menuId=MDC0201020403",
		"title": "선박투자회사 시세"
	},
	"12016": {
		"menuId": "/contents/MDC/MDI/mdiLoader/index.cmd?menuId=MDC0201020404",
		"title": "인프라투융자회사 시세"
	},
	"12017": {
		"menuId": "/contents/MDC/MDI/mdiLoader/index.cmd?menuId=MDC0201020405",
		"title": "수익증권 시세"
	},
	"12018": {
		"menuId": "/contents/MDC/MDI/mdiLoader/index.cmd?menuId=MDC0201020406",
		"title": "신주인수권증권 시세"
	},
	"12019": {
		"menuId": "/contents/MDC/MDI/mdiLoader/index.cmd?menuId=MDC0201020407",
		"title": "신주인수권증서 시세"
	},
	"12020": {
		"menuId": "/contents/MDC/MDI/mdiLoader/index.cmd?menuId=MDC0201020501",
		"title": "상장회사 상세검색"
	},
	"12021": {
		"menuId": "/contents/MDC/MDI/mdiLoader/index.cmd?menuId=MDC0201020502",
		"title": "PER/PBR/배당수익률(개별종목)"
	},
	"12022": {
		"menuId": "/contents/MDC/MDI/mdiLoader/index.cmd?menuId=MDC0201020503",
		"title": "외국인보유량 추이"
	},
	"12023": {
		"menuId": "/contents/MDC/MDI/mdiLoader/index.cmd?menuId=MDC0201020504",
		"title": "외국인보유량(개별종목)"
	},
	"12024": {
		"menuId": "/contents/MDC/MDI/mdiLoader/index.cmd?menuId=MDC0201020505",
		"title": "업종별 분포"
	},
	"12025": {
		"menuId": "/contents/MDC/MDI/mdiLoader/index.cmd?menuId=MDC0201020506",
		"title": "업종분류 현황"
	},
	"12026": {
		"menuId": "/contents/MDC/MDI/mdiLoader/index.cmd?menuId=MDC020102050701",
		"title": "주식 대용가"
	},
	"12027": {
		"menuId": "/contents/MDC/MDI/mdiLoader/index.cmd?menuId=MDC020102050702",
		"title": "수익증권 대용가"
	},
	"12028": {
		"menuId": "/contents/MDC/MDI/mdiLoader/index.cmd?menuId=MDC020102050703",
		"title": "뮤추얼펀드 대용가"
	},
	"13101": {
		"menuId": "/contents/MDC/MDI/mdiLoader/index.cmd?menuId=MDC0201030101",
		"title": "전종목 시세"
	},
	"13102": {
		"menuId": "/contents/MDC/MDI/mdiLoader/index.cmd?menuId=MDC0201030102",
		"title": "전종목 등락률"
	},
	"13103": {
		"menuId": "/contents/MDC/MDI/mdiLoader/index.cmd?menuId=MDC0201030103",
		"title": "개별종목 시세 추이"
	},
	"13104": {
		"menuId": "/contents/MDC/MDI/mdiLoader/index.cmd?menuId=MDC0201030104",
		"title": "전종목 기본정보"
	},
	"13105": {
		"menuId": "/contents/MDC/MDI/mdiLoader/index.cmd?menuId=MDC0201030105",
		"title": "개별종목 종합정보"
	},
	"13106": {
		"menuId": "/contents/MDC/MDI/mdiLoader/index.cmd?menuId=MDC0201030106",
		"title": "투자자별 거래실적"
	},
	"13107": {
		"menuId": "/contents/MDC/MDI/mdiLoader/index.cmd?menuId=MDC0201030107",
		"title": "투자자별 거래실적(개별종목)"
	},
	"13108": {
		"menuId": "/contents/MDC/MDI/mdiLoader/index.cmd?menuId=MDC0201030108",
		"title": "PDF(Portfolio Deposit File)"
	},
	"13109": {
		"menuId": "/contents/MDC/MDI/mdiLoader/index.cmd?menuId=MDC020103010901",
		"title": "ETF 상세검색"
	},
	"13110": {
		"menuId": "/contents/MDC/MDI/mdiLoader/index.cmd?menuId=MDC020103010902",
		"title": "액티브ETF 실적"
	},
	"13111": {
		"menuId": "/contents/MDC/MDI/mdiLoader/index.cmd?menuId=MDC020103010903",
		"title": "액티브ETF 편입자산현황"
	},
	"13112": {
		"menuId": "/contents/MDC/MDI/mdiLoader/index.cmd?menuId=MDC020103010904",
		"title": "추적오차율 추이"
	},
	"13113": {
		"menuId": "/contents/MDC/MDI/mdiLoader/index.cmd?menuId=MDC020103010905",
		"title": "괴리율 추이"
	},
	"13114": {
		"menuId": "/contents/MDC/MDI/mdiLoader/index.cmd?menuId=MDC020103010909",
		"title": "장마감 괴리율 추이"
	},
	"13115": {
		"menuId": "/contents/MDC/MDI/mdiLoader/index.cmd?menuId=MDC020103010906",
		"title": "합성ETF 거래상대방 위험"
	},
	"13116": {
		"menuId": "/contents/MDC/MDI/mdiLoader/index.cmd?menuId=MDC020103010907",
		"title": "합성ETF 기초지수 및 담보 관리"
	},
	"13117": {
		"menuId": "/contents/MDC/MDI/mdiLoader/index.cmd?menuId=MDC020103010908",
		"title": "분기별 LP평가"
	},
	"13201": {
		"menuId": "/contents/MDC/MDI/mdiLoader/index.cmd?menuId=MDC0201030201",
		"title": "전종목 시세"
	},
	"13202": {
		"menuId": "/contents/MDC/MDI/mdiLoader/index.cmd?menuId=MDC0201030202",
		"title": "전종목 등락률"
	},
	"13203": {
		"menuId": "/contents/MDC/MDI/mdiLoader/index.cmd?menuId=MDC0201030203",
		"title": "개별종목 시세 추이"
	},
	"13204": {
		"menuId": "/contents/MDC/MDI/mdiLoader/index.cmd?menuId=MDC0201030204",
		"title": "전종목 기본정보"
	},
	"13205": {
		"menuId": "/contents/MDC/MDI/mdiLoader/index.cmd?menuId=MDC0201030205",
		"title": "개별종목 종합정보"
	},
	"13206": {
		"menuId": "/contents/MDC/MDI/mdiLoader/index.cmd?menuId=MDC0201030206",
		"title": "투자자별 거래실적"
	},
	"13207": {
		"menuId": "/contents/MDC/MDI/mdiLoader/index.cmd?menuId=MDC0201030207",
		"title": "투자자별 거래실적(개별종목)"
	},
	"13208": {
		"menuId": "/contents/MDC/MDI/mdiLoader/index.cmd?menuId=MDC020103020801",
		"title": "ETN 상세검색"
	},
	"13209": {
		"menuId": "/contents/MDC/MDI/mdiLoader/index.cmd?menuId=MDC020103020802",
		"title": "기초지수 구성종목"
	},
	"13210": {
		"menuId": "/contents/MDC/MDI/mdiLoader/index.cmd?menuId=MDC020103020803",
		"title": "발행사 신용등급 및 NCR"
	},
	"13211": {
		"menuId": "/contents/MDC/MDI/mdiLoader/index.cmd?menuId=MDC020103030708",
		"title": "발행사 신용위험지표"
	},
	"13212": {
		"menuId": "/contents/MDC/MDI/mdiLoader/index.cmd?menuId=MDC020103020805",
		"title": "손실제한ETN 조기상환 조건"
	},
	"13213": {
		"menuId": "/contents/MDC/MDI/mdiLoader/index.cmd?menuId=MDC020103020806",
		"title": "손실제한ETN 레인지 어크루얼 참고사항"
	},
	"13214": {
		"menuId": "/contents/MDC/MDI/mdiLoader/index.cmd?menuId=MDC020103020807",
		"title": "괴리율 추이"
	},
	"13215": {
		"menuId": "/contents/MDC/MDI/mdiLoader/index.cmd?menuId=MDC020103020809",
		"title": "장마감 괴리율 추이"
	},
	"13216": {
		"menuId": "/contents/MDC/MDI/mdiLoader/index.cmd?menuId=MDC020103020808",
		"title": "월별 LP평가"
	},
	"13301": {
		"menuId": "/contents/MDC/MDI/mdiLoader/index.cmd?menuId=MDC0201030301",
		"title": "전종목 시세"
	},
	"13302": {
		"menuId": "/contents/MDC/MDI/mdiLoader/index.cmd?menuId=MDC0201030302",
		"title": "개별종목 시세 추이"
	},
	"13303": {
		"menuId": "/contents/MDC/MDI/mdiLoader/index.cmd?menuId=MDC0201030303",
		"title": "전종목 기본정보"
	},
	"13304": {
		"menuId": "/contents/MDC/MDI/mdiLoader/index.cmd?menuId=MDC0201030304",
		"title": "개별종목 종합정보"
	},
	"13305": {
		"menuId": "/contents/MDC/MDI/mdiLoader/index.cmd?menuId=MDC0201030305",
		"title": "투자자별 거래실적"
	},
	"13306": {
		"menuId": "/contents/MDC/MDI/mdiLoader/index.cmd?menuId=MDC0201030306",
		"title": "기초자산별 거래실적"
	},
	"13307": {
		"menuId": "/contents/MDC/MDI/mdiLoader/index.cmd?menuId=MDC020103030701",
		"title": "개별종목 잔존만기현황"
	},
	"13308": {
		"menuId": "/contents/MDC/MDI/mdiLoader/index.cmd?menuId=MDC020103030702",
		"title": "개별종목 만기손익현황"
	},
	"13309": {
		"menuId": "/contents/MDC/MDI/mdiLoader/index.cmd?menuId=MDC020103030704",
		"title": "조기종료 접근도"
	},
	"13310": {
		"menuId": "/contents/MDC/MDI/mdiLoader/index.cmd?menuId=MDC020103030705",
		"title": "조기종료 발생내역"
	},
	"13311": {
		"menuId": "/contents/MDC/MDI/mdiLoader/index.cmd?menuId=MDC020103030706",
		"title": "기초자산별 상장현황"
	},
	"13312": {
		"menuId": "/contents/MDC/MDI/mdiLoader/index.cmd?menuId=MDC020103030707",
		"title": "발행사별 상장현황"
	},
	"13313": {
		"menuId": "/contents/MDC/MDI/mdiLoader/index.cmd?menuId=MDC020103030709",
		"title": "분기별 LP평가"
	},
	"14001": {
		"menuId": "/contents/MDC/MDI/mdiLoader/index.cmd?menuId=MDC0201040101",
		"title": "전종목 시세"
	},
	"14002": {
		"menuId": "/contents/MDC/MDI/mdiLoader/index.cmd?menuId=MDC0201040102",
		"title": "개별종목 시세 추이"
	},
	"14003": {
		"menuId": "/contents/MDC/MDI/mdiLoader/index.cmd?menuId=MDC0201040201",
		"title": "전종목 기본정보"
	},
	"14004": {
		"menuId": "/contents/MDC/MDI/mdiLoader/index.cmd?menuId=MDC0201040202",
		"title": "개별종목 종합정보"
	},
	"14005": {
		"menuId": "/contents/MDC/MDI/mdiLoader/index.cmd?menuId=MDC0201040301",
		"title": "종류별 거래실적"
	},
	"14006": {
		"menuId": "/contents/MDC/MDI/mdiLoader/index.cmd?menuId=MDC0201040302",
		"title": "투자자별 거래실적"
	},
	"14007": {
		"menuId": "/contents/MDC/MDI/mdiLoader/index.cmd?menuId=MDC0201040303",
		"title": "국채지표종목 거래실적"
	},
	"14008": {
		"menuId": "/contents/MDC/MDI/mdiLoader/index.cmd?menuId=MDC0201040304",
		"title": "Repo 거래실적"
	},
	"14009": {
		"menuId": "/contents/MDC/MDI/mdiLoader/index.cmd?menuId=MDC0201040401",
		"title": "개별종목 시가평가 추이"
	},
	"14010": {
		"menuId": "/contents/MDC/MDI/mdiLoader/index.cmd?menuId=MDC0201040402",
		"title": "소액채권 신고가격 추이"
	},
	"14011": {
		"menuId": "/contents/MDC/MDI/mdiLoader/index.cmd?menuId=MDC020104040301",
		"title": "상장채권 상세검색"
	},
	"14012": {
		"menuId": "/contents/MDC/MDI/mdiLoader/index.cmd?menuId=MDC020104040302",
		"title": "상장채권 발행정보"
	},
	"14013": {
		"menuId": "/contents/MDC/MDI/mdiLoader/index.cmd?menuId=MDC020104040303",
		"title": "상장유형별 내역"
	},
	"14014": {
		"menuId": "/contents/MDC/MDI/mdiLoader/index.cmd?menuId=MDC020104040304",
		"title": "상장금액조정 내역"
	},
	"14015": {
		"menuId": "/contents/MDC/MDI/mdiLoader/index.cmd?menuId=MDC020104040305",
		"title": "중도상환"
	},
	"14016": {
		"menuId": "/contents/MDC/MDI/mdiLoader/index.cmd?menuId=MDC020104040306",
		"title": "채권상장폐지"
	},
	"14017": {
		"menuId": "/contents/MDC/MDI/mdiLoader/index.cmd?menuId=MDC020104040401",
		"title": "장외 채권수익률"
	},
	"14018": {
		"menuId": "/contents/MDC/MDI/mdiLoader/index.cmd?menuId=MDC020104040402",
		"title": "지표수익률"
	},
	"14019": {
		"menuId": "/contents/MDC/MDI/mdiLoader/index.cmd?menuId=MDC020104040403",
		"title": "스트립 단기금리"
	},
	"14020": {
		"menuId": "/contents/MDC/MDI/mdiLoader/index.cmd?menuId=MDC020104040501",
		"title": "채권 대용가"
	},
	"14021": {
		"menuId": "/contents/MDC/MDI/mdiLoader/index.cmd?menuId=MDC020104040502",
		"title": "발행기관별 채권 대용가"
	},
	"14022": {
		"menuId": "/contents/MDC/MDI/mdiLoader/index.cmd?menuId=MDC020104040503",
		"title": "유형별 채권 대용가"
	},
	"14023": {
		"menuId": "/contents/MDC/MDI/mdiLoader/index.cmd?menuId=MDC020104040601",
		"title": "발행기관별 신용등급"
	},
	"14024": {
		"menuId": "/contents/MDC/MDI/mdiLoader/index.cmd?menuId=MDC020104040602",
		"title": "신용등급별 상장현황"
	},
	"14025": {
		"menuId": "/contents/MDC/MDI/mdiLoader/index.cmd?menuId=MDC020104040701",
		"title": "전환사채 투자지표"
	},
	"14026": {
		"menuId": "/contents/MDC/MDI/mdiLoader/index.cmd?menuId=MDC020104040702",
		"title": "주식관련채권 권리행사"
	},
	"14027": {
		"menuId": "/contents/MDC/MDI/mdiLoader/index.cmd?menuId=MDC020104040703",
		"title": "주식관련채권 행사가액"
	},
	"15001": {
		"menuId": "/contents/MDC/MDI/mdiLoader/index.cmd?menuId=MDC0201050101",
		"title": "전종목 시세"
	},
	"15002": {
		"menuId": "/contents/MDC/MDI/mdiLoader/index.cmd?menuId=MDC0201050102",
		"title": "개별종목 시세 추이"
	},
	"15003": {
		"menuId": "/contents/MDC/MDI/mdiLoader/index.cmd?menuId=MDC0201050103",
		"title": "최근월물 시세 추이(선물)"
	},
	"15004": {
		"menuId": "/contents/MDC/MDI/mdiLoader/index.cmd?menuId=MDC0201050201",
		"title": "전종목 기본정보"
	},
	"15005": {
		"menuId": "/contents/MDC/MDI/mdiLoader/index.cmd?menuId=MDC0201050202",
		"title": "개별종목 종합정보"
	},
	"15006": {
		"menuId": "/contents/MDC/MDI/mdiLoader/index.cmd?menuId=MDC0201050301",
		"title": "전체상품 거래실적"
	},
	"15007": {
		"menuId": "/contents/MDC/MDI/mdiLoader/index.cmd?menuId=MDC0201050302",
		"title": "투자자별 거래실적"
	},
	"15008": {
		"menuId": "/contents/MDC/MDI/mdiLoader/index.cmd?menuId=MDC0201050303",
		"title": "협의대량거래실적 추이"
	},
	"15009": {
		"menuId": "/contents/MDC/MDI/mdiLoader/index.cmd?menuId=MDC0201050304",
		"title": "기초자산별 거래실적(주식선물/옵션)"
	},
	"15010": {
		"menuId": "/contents/MDC/MDI/mdiLoader/index.cmd?menuId=MDC0201050401",
		"title": "베이시스 추이(선물)"
	},
	"15011": {
		"menuId": "/contents/MDC/MDI/mdiLoader/index.cmd?menuId=MDC0201050402",
		"title": "내재변동성 추이(옵션)"
	},
	"15012": {
		"menuId": "/contents/MDC/MDI/mdiLoader/index.cmd?menuId=MDC0201050403",
		"title": "P/C Ratio 추이(옵션)"
	},
	"15013": {
		"menuId": "/contents/MDC/MDI/mdiLoader/index.cmd?menuId=MDC0201050404",
		"title": "행사가격/만기별 가격표(옵션)"
	},
	"15014": {
		"menuId": "/contents/MDC/MDI/mdiLoader/index.cmd?menuId=MDC020105040501",
		"title": "돈육시세 동향"
	},
	"16207": {
		"menuId": "/contents/MDC/MDI/mdiLoader/index.cmd?menuId=MDC0201060207",
		"title": "국제금시세 동향"
	},
	"15015": {
		"menuId": "/contents/MDC/MDI/mdiLoader/index.cmd?menuId=MDC020105040601",
		"title": "최종결제가격 급변"
	},
	"15016": {
		"menuId": "/contents/MDC/MDI/mdiLoader/index.cmd?menuId=MDC020105040602",
		"title": "낮은 권리행사 비율"
	},
	"15017": {
		"menuId": "/contents/MDC/MDI/mdiLoader/index.cmd?menuId=MDC0201050407",
		"title": "증거금률 및 산출변수 변경내역"
	},
	"16101": {
		"menuId": "/contents/MDC/MDI/mdiLoader/index.cmd?menuId=MDC0201060101",
		"title": "전종목 기본정보"
	},
	"16102": {
		"menuId": "/contents/MDC/MDI/mdiLoader/index.cmd?menuId=MDC0201060102",
		"title": "유종별 시세 추이"
	},
	"16103": {
		"menuId": "/contents/MDC/MDI/mdiLoader/index.cmd?menuId=MDC0201060103",
		"title": "참가자별 거래실적"
	},
	"16104": {
		"menuId": "/contents/MDC/MDI/mdiLoader/index.cmd?menuId=MDC020106010401",
		"title": "국내유가(주유소) 동향"
	},
	"16105": {
		"menuId": "/contents/MDC/MDI/mdiLoader/index.cmd?menuId=MDC020106010402",
		"title": "국제유가 동향"
	},
	"16201": {
		"menuId": "/contents/MDC/MDI/mdiLoader/index.cmd?menuId=MDC0201060201",
		"title": "전종목 시세"
	},
	"16202": {
		"menuId": "/contents/MDC/MDI/mdiLoader/index.cmd?menuId=MDC0201060202",
		"title": "개별종목 시세 추이"
	},
	"16203": {
		"menuId": "/contents/MDC/MDI/mdiLoader/index.cmd?menuId=MDC0201060203",
		"title": "전종목 기본정보"
	},
	"16204": {
		"menuId": "/contents/MDC/MDI/mdiLoader/index.cmd?menuId=MDC0201060204",
		"title": "개별종목 종합정보"
	},
	"16205": {
		"menuId": "/contents/MDC/MDI/mdiLoader/index.cmd?menuId=MDC0201060205",
		"title": "투자자별 거래실적"
	},
	"16206": {
		"menuId": "/contents/MDC/MDI/mdiLoader/index.cmd?menuId=MDC0201060206",
		"title": "협의대량거래실적 추이"
	},
	"16301": {
		"menuId": "/contents/MDC/MDI/mdiLoader/index.cmd?menuId=MDC0201060301",
		"title": "전종목 시세"
	},
	"16302": {
		"menuId": "/contents/MDC/MDI/mdiLoader/index.cmd?menuId=MDC0201060302",
		"title": "개별종목 시세 추이"
	},
	"16303": {
		"menuId": "/contents/MDC/MDI/mdiLoader/index.cmd?menuId=MDC0201060303",
		"title": "전종목 기본정보"
	},
	"16304": {
		"menuId": "/contents/MDC/MDI/mdiLoader/index.cmd?menuId=MDC0201060304",
		"title": "개별종목 종합정보"
	},
	"17101": {
		"menuId": "/contents/MDC/MDI/mdiLoader/index.cmd?menuId=MDC0201070201",
		"title": "전종목 시세"
	},
	"17102": {
		"menuId": "/contents/MDC/MDI/mdiLoader/index.cmd?menuId=MDC0201070202",
		"title": "개별종목 시세 추이"
	},
	"17103": {
		"menuId": "/contents/MDC/MDI/mdiLoader/index.cmd?menuId=MDC0201070203",
		"title": "장개시전협의거래실적 추이"
	},
	"17104": {
		"menuId": "/contents/MDC/MDI/mdiLoader/index.cmd?menuId=MDC0201070204",
		"title": "권리유형별 거래실적 추이"
	},
	"17105": {
		"menuId": "/contents/MDC/MDI/mdiLoader/index.cmd?menuId=MDC0201070205",
		"title": "권리유형별 거래실적 추이(월)"
	},
	"17106": {
		"menuId": "/contents/MDC/MDI/mdiLoader/index.cmd?menuId=MDC0201070206",
		"title": "EURO STOXX 50 시세 추이"
	},
	"17107": {
		"menuId": "/contents/MDC/MDI/mdiLoader/index.cmd?menuId=MDC0201070207",
		"title": "만기별 가격표(옵션)"
	},
	"17108": {
		"menuId": "/contents/MDC/MDI/mdiLoader/index.cmd?menuId=MDC0201070208",
		"title": "주요통계 추이(옵션)"
	},
	"17109": {
		"menuId": "/contents/MDC/MDI/mdiLoader/index.cmd?menuId=MDC0201070301",
		"title": "개별종목 종합정보"
	},
	"20001": {
		"menuId": "/contents/MDC/MDI/mdiLoader/index.cmd?menuId=MDC02020101",
		"title": "신규상장종목 현황"
	},
	"20002": {
		"menuId": "/contents/MDC/MDI/mdiLoader/index.cmd?menuId=MDC02020102",
		"title": "상장이후 최고/최저가"
	},
	"20003": {
		"menuId": "/contents/MDC/MDI/mdiLoader/index.cmd?menuId=MDC02020103",
		"title": "공모가대비 등락률"
	},
	"20004": {
		"menuId": "/contents/MDC/MDI/mdiLoader/index.cmd?menuId=MDC02020301",
		"title": "자사주취득/처분종목 현황"
	},
	"20005": {
		"menuId": "/contents/MDC/MDI/mdiLoader/index.cmd?menuId=MDC02020302",
		"title": "자사주취득/처분 내역(개별종목)"
	},
	"20006": {
		"menuId": "/contents/MDC/MDI/mdiLoader/index.cmd?menuId=MDC02020303",
		"title": "공시일전후 등락률"
	},
	"20007": {
		"menuId": "/contents/MDC/MDI/mdiLoader/index.cmd?menuId=MDC02020401",
		"title": "배당종목 현황"
	},
	"20008": {
		"menuId": "/contents/MDC/MDI/mdiLoader/index.cmd?menuId=MDC02020501",
		"title": "기업집단별 현황"
	},
	"20009": {
		"menuId": "/contents/MDC/MDI/mdiLoader/index.cmd?menuId=MDC02020502",
		"title": "기업집단별 기업 현황"
	},
	"20010": {
		"menuId": "/contents/MDC/MDI/mdiLoader/index.cmd?menuId=MDC02020601",
		"title": "매매거래정지종목 현황"
	},
	"20011": {
		"menuId": "/contents/MDC/MDI/mdiLoader/index.cmd?menuId=MDC02020602",
		"title": "매매거래정지 내역(개별종목)"
	},
	"20012": {
		"menuId": "/contents/MDC/MDI/mdiLoader/index.cmd?menuId=MDC02020701",
		"title": "관리종목 현황"
	},
	"20013": {
		"menuId": "/contents/MDC/MDI/mdiLoader/index.cmd?menuId=MDC02020702",
		"title": "관리종목 지정 내역(개별종목)"
	},
	"20014": {
		"menuId": "/contents/MDC/MDI/mdiLoader/index.cmd?menuId=MDC02020703",
		"title": "지정일전후 등락률"
	},
	"20015": {
		"menuId": "/contents/MDC/MDI/mdiLoader/index.cmd?menuId=MDC02020801",
		"title": "투자주의환기종목(코) 현황"
	},
	"20016": {
		"menuId": "/contents/MDC/MDI/mdiLoader/index.cmd?menuId=MDC02020802",
		"title": "투자주의환기종목(코) 지정 내역(개별종목)"
	},
	"20017": {
		"menuId": "/contents/MDC/MDI/mdiLoader/index.cmd?menuId=MDC02020803",
		"title": "지정일전후 등락률"
	},
	"20018": {
		"menuId": "/contents/MDC/MDI/mdiLoader/index.cmd?menuId=MDC02020901",
		"title": "불성실공시법인 현황"
	},
	"20019": {
		"menuId": "/contents/MDC/MDI/mdiLoader/index.cmd?menuId=MDC02020902",
		"title": "불성실공시법인 지정 내역(개별종목)"
	},
	"20020": {
		"menuId": "/contents/MDC/MDI/mdiLoader/index.cmd?menuId=MDC02020903",
		"title": "지정일전후 등락률"
	},
	"20021": {
		"menuId": "/contents/MDC/MDI/mdiLoader/index.cmd?menuId=MDC02021401",
		"title": "초저유동성종목 현황"
	},
	"20022": {
		"menuId": "/contents/MDC/MDI/mdiLoader/index.cmd?menuId=MDC02021601",
		"title": "상장주식수 부족 우선주 현황"
	},
	"20023": {
		"menuId": "/contents/MDC/MDI/mdiLoader/index.cmd?menuId=MDC02021501",
		"title": "변동성완화장치 발동종목 현황"
	},
	"20024": {
		"menuId": "/contents/MDC/MDI/mdiLoader/index.cmd?menuId=MDC02021001",
		"title": "단기과열종목 현황"
	},
	"20025": {
		"menuId": "/contents/MDC/MDI/mdiLoader/index.cmd?menuId=MDC02021002",
		"title": "단기과열종목 지정 내역(개별종목)"
	},
	"20026": {
		"menuId": "/contents/MDC/MDI/mdiLoader/index.cmd?menuId=MDC02021003",
		"title": "지정일전후 등락률"
	},
	"20027": {
		"menuId": "/contents/MDC/MDI/mdiLoader/index.cmd?menuId=MDC0202110101",
		"title": "투자주의종목 현황"
	},
	"20028": {
		"menuId": "/contents/MDC/MDI/mdiLoader/index.cmd?menuId=MDC0202110102",
		"title": "투자주의종목 지정 내역(개별종목)"
	},
	"20029": {
		"menuId": "/contents/MDC/MDI/mdiLoader/index.cmd?menuId=MDC0202110103",
		"title": "지정일전후 등락률"
	},
	"20030": {
		"menuId": "/contents/MDC/MDI/mdiLoader/index.cmd?menuId=MDC0202110201",
		"title": "투자경고종목 현황"
	},
	"20031": {
		"menuId": "/contents/MDC/MDI/mdiLoader/index.cmd?menuId=MDC0202110202",
		"title": "투자경고종목 지정 내역(개별종목)"
	},
	"20032": {
		"menuId": "/contents/MDC/MDI/mdiLoader/index.cmd?menuId=MDC0202110203",
		"title": "지정일전후 등락률"
	},
	"20033": {
		"menuId": "/contents/MDC/MDI/mdiLoader/index.cmd?menuId=MDC0202110301",
		"title": "투자위험종목 현황"
	},
	"20034": {
		"menuId": "/contents/MDC/MDI/mdiLoader/index.cmd?menuId=MDC0202110302",
		"title": "투자위험종목 지정 내역(개별종목)"
	},
	"20035": {
		"menuId": "/contents/MDC/MDI/mdiLoader/index.cmd?menuId=MDC0202110303",
		"title": "지정일전후 등락률"
	},
	"20036": {
		"menuId": "/contents/MDC/MDI/mdiLoader/index.cmd?menuId=MDC02021201",
		"title": "정리매매종목 현황"
	},
	"20037": {
		"menuId": "/contents/MDC/MDI/mdiLoader/index.cmd?menuId=MDC02021301",
		"title": "상장폐지종목 현황"
	},
	"20038": {
		"menuId": "/contents/MDC/MDI/mdiLoader/index.cmd?menuId=MDC02021302",
		"title": "상장폐지종목 시세 추이"
	},
	"31001": {
		"menuId": "/contents/MDC/MDI/mdiLoader/index.cmd?menuId=MDC02030101",
		"title": "개별종목 공매도 종합정보"
	},
	"32001": {
		"menuId": "/contents/MDC/MDI/mdiLoader/index.cmd?menuId=MDC02030201",
		"title": "개별종목 공매도 거래"
	},
	"32002": {
		"menuId": "/contents/MDC/MDI/mdiLoader/index.cmd?menuId=MDC02030202",
		"title": "개별업종 공매도 거래"
	},
	"32003": {
		"menuId": "/contents/MDC/MDI/mdiLoader/index.cmd?menuId=MDC02030203",
		"title": "투자자별 공매도 거래"
	},
	"32004": {
		"menuId": "/contents/MDC/MDI/mdiLoader/index.cmd?menuId=MDC02030204",
		"title": "공매도 거래 상위 50종목"
	},
	"33001": {
		"menuId": "/contents/MDC/MDI/mdiLoader/index.cmd?menuId=MDC02030301",
		"title": "개별종목 공매도 잔고"
	},
	"33002": {
		"menuId": "/contents/MDC/MDI/mdiLoader/index.cmd?menuId=MDC02030302",
		"title": "개별업종 공매도 잔고"
	},
	"33003": {
		"menuId": "/contents/MDC/MDI/mdiLoader/index.cmd?menuId=MDC02030303",
		"title": "공매도 잔고 대량보유자"
	},
	"33004": {
		"menuId": "/contents/MDC/MDI/mdiLoader/index.cmd?menuId=MDC02030304",
		"title": "공매도 잔고 상위 50종목"
	},
	"34001": {
		"menuId": "/contents/MDC/MDI/mdiLoader/index.cmd?menuId=MDC02030401",
		"title": "공매도 과열종목"
	},
	"34002": {
		"menuId": "/contents/MDC/MDI/mdiLoader/index.cmd?menuId=MDC02030402",
		"title": "공매도 과열종목 지정기준"
	}
}